[{"__symbolic":"module","version":4,"metadata":{"fadeIn":{"__symbolic":"call","expression":{"__symbolic":"reference","module":"@angular/animations","name":"animation","line":24,"character":43},"arguments":[[{"__symbolic":"call","expression":{"__symbolic":"reference","module":"@angular/animations","name":"style","line":5,"character":4},"arguments":[{"opacity":"{{startOpacity}}"}]},{"__symbolic":"call","expression":{"__symbolic":"reference","module":"@angular/animations","name":"animate","line":8,"character":4},"arguments":["{{duration}} {{delay}} {{easing}}",{"__symbolic":"call","expression":{"__symbolic":"reference","module":"@angular/animations","name":"style","line":10,"character":8},"arguments":[{"opacity":"{{endOpacity}}"}]}]}],{"params":{"delay":"0s","duration":"350ms","easing":{"__symbolic":"select","expression":{"__symbolic":"reference","module":"../easings","name":"EaseOut","line":19,"character":12},"member":"sine"},"endOpacity":1,"startOpacity":0}}]},"fadeOut":{"__symbolic":"call","expression":{"__symbolic":"reference","module":"@angular/animations","name":"animation","line":28,"character":44},"arguments":[[{"__symbolic":"call","expression":{"__symbolic":"reference","module":"@angular/animations","name":"style","line":5,"character":4},"arguments":[{"opacity":"{{startOpacity}}"}]},{"__symbolic":"call","expression":{"__symbolic":"reference","module":"@angular/animations","name":"animate","line":8,"character":4},"arguments":["{{duration}} {{delay}} {{easing}}",{"__symbolic":"call","expression":{"__symbolic":"reference","module":"@angular/animations","name":"style","line":10,"character":8},"arguments":[{"opacity":"{{endOpacity}}"}]}]}],{"params":{"delay":"0s","duration":"350ms","easing":{"__symbolic":"select","expression":{"__symbolic":"reference","module":"../easings","name":"EaseOut","line":32,"character":16},"member":"sine"},"endOpacity":0,"startOpacity":1}}]}}}]